fern/__init__.py
python_fern-0.1.0.dist-info/LICENSE.md
python_fern-0.1.0.dist-info/METADATA
python_fern-0.1.0.dist-info/WHEEL
python_fern-0.1.0.dist-info/entry_points.txt
python_fern-0.1.0.dist-info/RECORD
